{
  "data": [
    {
      "key": "local_distributions",
      "value": [
        {
          "key": "cell_distributions",
          "value": [
          ]
        },
        {
          "key": "region_distributions",
          "value": [
            {
              "key": "region_distribution",
              "value": [
                {
                  "key": "$PBGNAME",
                  "value": "local_region_dist_impasse_forest"
                },
                {
                  "key": "$PBGMAP",
                  "value": "map_gen\\distribution\\local_region_distribution"
                }
              ]
            }
          ]
        }
      ]
    },
    {
      "key": "pbgid",
      "value": 172954
    }
  ]
}