{
  "data": [
    {
      "key": "name",
      "value": ""
    },
    {
      "key": "items",
      "value": [
        {
          "key": "item",
          "value": [
            {
              "key": "$PBGNAME",
              "value": "hun_m05_hoh_campaign_life"
            },
            {
              "key": "$PBGMAP",
              "value": "generic_inventory_item"
            }
          ]
        },
        {
          "key": "item",
          "value": [
            {
              "key": "$PBGNAME",
              "value": "hun_m05_txt_tbd5"
            },
            {
              "key": "$PBGMAP",
              "value": "generic_inventory_item"
            }
          ]
        },
        {
          "key": "item",
          "value": [
            {
              "key": "$PBGNAME",
              "value": "hun_m05_cp"
            },
            {
              "key": "$PBGMAP",
              "value": "generic_inventory_item"
            }
          ]
        }
      ]
    },
    {
      "key": "inventory_item_bundle_type",
      "value": "Level"
    },
    {
      "key": "server_id",
      "value": 866
    }
  ]
}