{
  "data": [
    {
      "key": "pbgid",
      "value": 186311
    },
    {
      "key": "erosion_pass",
      "value": [
        {
          "key": "droplet_chance",
          "value": 0.5
        },
        {
          "key": "droplet",
          "value": [
            {
              "key": "$PBGNAME",
              "value": "droplet_soft_features"
            },
            {
              "key": "$PBGMAP",
              "value": "map_gen\\droplet"
            }
          ]
        },
        {
          "key": "pass_number",
          "value": 4
        },
        {
          "key": "min_height_percentile",
          "value": 0.6
        }
      ]
    }
  ]
}